stronk/__init__.py
stronk/__main__.py
stronk/constants.py
stronk/stronk.py
stronk-1.1.4.dist-info/LICENSE
stronk-1.1.4.dist-info/METADATA
stronk-1.1.4.dist-info/WHEEL
stronk-1.1.4.dist-info/entry_points.txt
stronk-1.1.4.dist-info/top_level.txt
stronk-1.1.4.dist-info/RECORD
