Metadata-Version: 2.1
Name: stronk
Version: 1.1.4
Summary: Strong key generator
Home-page: https://github.com/brianrthompson/stronk
Author: Brian Thompson
Author-email: brianrt23@gmail.com
License: MIT
Platform: UNKNOWN
Classifier: License :: OSI Approved :: MIT License
Classifier: Programming Language :: Python :: 3
Classifier: Programming Language :: Python :: 3.6
